{
    "renamePlaylist": "Çalma Listesini Yeniden Adlandır",
    "networkError1": "Oops ağ hatası!",
    "libSongs": "Kütüphane Şarkıları",
    "communityplaylists": "Topluluk çalma listeleri",
    "libAlbums": "Kütüphane Albümleri",
    "enqueueAll": "Tümünü kuyruğa al",
    "create": "Yaratmak",
    "noBookmarks": "Yer işaretleri yok!",
    "playlists": "Çalma Listeleri",
    "rename": "Yeniden adlandır",
    "items": "öğeler",
    "startRadio": "Radyo başlat",
    "libArtists": "Kütüphane Sanatçıları",
    "removePlaylist": "Çalma listesini kaldır",
    "addToPlaylist": "Çalma listesine ekle",
    "cachedOrOffline": "Önbelleğe Alınmış/Çevrimdışı",
    "retry": "Tekrar dene",
    "artists": "Sanatçılar",
    "albums": "Albümler",
    "recentlyPlayed": "Son çalınan",
    "createnAdd": "Oluştur ve ekle",
    "singles": "Single'lar",
    "emptyPlaylist": "Çalma Listesini Boşalt!",
    "favorites": "Favoriler",
    "home": "Anasayfa",
    "cancel": "İptal et",
    "libPlaylists": "Kütüphane Playlists",
    "CreateNewPlaylist": "Çalma listesi oluştur",
    "playNext": "Bir sonra çal",
    "songs": "Şarkılar",
    "settings": "Ayarlar",
    "noOfflineSong": "Çevrimdışı şarkı yok!",
    "featuredplaylists": "Öne çıkan listeler"
}
